karborclient/__init__.py
karborclient/client.py
karborclient/i18n.py
karborclient/shell.py
karborclient/utils.py
karborclient/version.py
karborclient/common/__init__.py
karborclient/common/base.py
karborclient/common/http.py
karborclient/common/utils.py
karborclient/common/apiclient/__init__.py
karborclient/common/apiclient/auth.py
karborclient/common/apiclient/base.py
karborclient/common/apiclient/client.py
karborclient/common/apiclient/exceptions.py
karborclient/common/apiclient/fake_client.py
karborclient/osc/__init__.py
karborclient/osc/plugin.py
karborclient/osc/v1/__init__.py
karborclient/osc/v1/checkpoints.py
karborclient/osc/v1/operation_logs.py
karborclient/osc/v1/plans.py
karborclient/osc/v1/protectables.py
karborclient/osc/v1/providers.py
karborclient/osc/v1/quota_classes.py
karborclient/osc/v1/quotas.py
karborclient/osc/v1/restores.py
karborclient/osc/v1/scheduled_operations.py
karborclient/osc/v1/services.py
karborclient/osc/v1/triggers.py
karborclient/osc/v1/verifications.py
karborclient/tests/__init__.py
karborclient/tests/unit/__init__.py
karborclient/tests/unit/base.py
karborclient/tests/unit/fakes.py
karborclient/tests/unit/test_http.py
karborclient/tests/unit/test_karborclient.py
karborclient/tests/unit/test_shell.py
karborclient/tests/unit/osc/__init__.py
karborclient/tests/unit/osc/v1/__init__.py
karborclient/tests/unit/osc/v1/fakes.py
karborclient/tests/unit/osc/v1/test_checkpoints.py
karborclient/tests/unit/osc/v1/test_operation_logs.py
karborclient/tests/unit/osc/v1/test_plans.py
karborclient/tests/unit/osc/v1/test_protectables.py
karborclient/tests/unit/osc/v1/test_providers.py
karborclient/tests/unit/osc/v1/test_quota_classes.py
karborclient/tests/unit/osc/v1/test_quotas.py
karborclient/tests/unit/osc/v1/test_restores.py
karborclient/tests/unit/osc/v1/test_scheduledoperations.py
karborclient/tests/unit/osc/v1/test_services.py
karborclient/tests/unit/osc/v1/test_triggers.py
python_karborclient-2.1.0.dist-info/DESCRIPTION.rst
python_karborclient-2.1.0.dist-info/METADATA
python_karborclient-2.1.0.dist-info/RECORD
python_karborclient-2.1.0.dist-info/WHEEL
python_karborclient-2.1.0.dist-info/entry_points.txt
python_karborclient-2.1.0.dist-info/metadata.json
python_karborclient-2.1.0.dist-info/pbr.json
python_karborclient-2.1.0.dist-info/top_level.txt
