Metadata-Version: 2.0
Name: python-karborclient
Version: 2.1.0
Summary: Python client library for Karbor API
Home-page: https://docs.openstack.org/python-karborclient/latest/
Author: OpenStack
Author-email: openstack-discuss@lists.openstack.org
License: UNKNOWN
Platform: UNKNOWN
Classifier: Environment :: OpenStack
Classifier: Intended Audience :: Information Technology
Classifier: Intended Audience :: System Administrators
Classifier: License :: OSI Approved :: Apache Software License
Classifier: Operating System :: POSIX :: Linux
Classifier: Programming Language :: Python
Classifier: Programming Language :: Python :: Implementation :: CPython
Classifier: Programming Language :: Python :: 3 :: Only
Classifier: Programming Language :: Python :: 3
Classifier: Programming Language :: Python :: 3.6
Classifier: Programming Language :: Python :: 3.7
Requires-Python: >=3.6
Requires-Dist: Babel (!=2.4.0,>=2.3.4)
Requires-Dist: PrettyTable (<0.8,>=0.7.1)
Requires-Dist: keystoneauth1 (>=3.4.0)
Requires-Dist: osc-lib (>=1.8.0)
Requires-Dist: oslo.i18n (>=3.15.3)
Requires-Dist: oslo.log (>=3.36.0)
Requires-Dist: oslo.utils (>=3.33.0)
Requires-Dist: pbr (!=2.1.0,>=2.0.0)
Requires-Dist: requests (>=2.14.2)
Requires-Dist: simplejson (>=3.5.1)
Requires-Dist: six (>=1.10.0)
